{"nodes": [{"id": "c_users_tanis_onedrive_documents_ai_ml_agentic_ai_hireloop_hireloop_frontend_src_components_ui_tabs_jsx", "label": "tabs.jsx", "file_type": "code", "source_file": "C:\\Users\\tanis\\OneDrive\\Documents\\Ai-Ml\\Agentic Ai\\HireLoop\\HireLoop\\frontend\\src\\components\\ui\\tabs.jsx", "source_location": "L1"}, {"id": "ui_tabs_tabs", "label": "Tabs()", "file_type": "code", "source_file": "C:\\Users\\tanis\\OneDrive\\Documents\\Ai-Ml\\Agentic Ai\\HireLoop\\HireLoop\\frontend\\src\\components\\ui\\tabs.jsx", "source_location": "L8"}, {"id": "ui_tabs_tabslist", "label": "TabsList()", "file_type": "code", "source_file": "C:\\Users\\tanis\\OneDrive\\Documents\\Ai-Ml\\Agentic Ai\\HireLoop\\HireLoop\\frontend\\src\\components\\ui\\tabs.jsx", "source_location": "L37"}, {"id": "ui_tabs_tabstrigger", "label": "TabsTrigger()", "file_type": "code", "source_file": "C:\\Users\\tanis\\OneDrive\\Documents\\Ai-Ml\\Agentic Ai\\HireLoop\\HireLoop\\frontend\\src\\components\\ui\\tabs.jsx", "source_location": "L51"}, {"id": "ui_tabs_tabscontent", "label": "TabsContent()", "file_type": "code", "source_file": "C:\\Users\\tanis\\OneDrive\\Documents\\Ai-Ml\\Agentic Ai\\HireLoop\\HireLoop\\frontend\\src\\components\\ui\\tabs.jsx", "source_location": "L69"}], "edges": [{"source": "c_users_tanis_onedrive_documents_ai_ml_agentic_ai_hireloop_hireloop_frontend_src_components_ui_tabs_jsx", "target": "tabs", "relation": "imports_from", "confidence": "EXTRACTED", "source_file": "C:\\Users\\tanis\\OneDrive\\Documents\\Ai-Ml\\Agentic Ai\\HireLoop\\HireLoop\\frontend\\src\\components\\ui\\tabs.jsx", "source_location": "L3", "weight": 1.0}, {"source": "c_users_tanis_onedrive_documents_ai_ml_agentic_ai_hireloop_hireloop_frontend_src_components_ui_tabs_jsx", "target": "class_variance_authority", "relation": "imports_from", "confidence": "EXTRACTED", "source_file": "C:\\Users\\tanis\\OneDrive\\Documents\\Ai-Ml\\Agentic Ai\\HireLoop\\HireLoop\\frontend\\src\\components\\ui\\tabs.jsx", "source_location": "L4", "weight": 1.0}, {"source": "c_users_tanis_onedrive_documents_ai_ml_agentic_ai_hireloop_hireloop_frontend_src_components_ui_tabs_jsx", "target": "utils", "relation": "imports_from", "confidence": "EXTRACTED", "source_file": "C:\\Users\\tanis\\OneDrive\\Documents\\Ai-Ml\\Agentic Ai\\HireLoop\\HireLoop\\frontend\\src\\components\\ui\\tabs.jsx", "source_location": "L6", "weight": 1.0}, {"source": "c_users_tanis_onedrive_documents_ai_ml_agentic_ai_hireloop_hireloop_frontend_src_components_ui_tabs_jsx", "target": "ui_tabs_tabs", "relation": "contains", "confidence": "EXTRACTED", "source_file": "C:\\Users\\tanis\\OneDrive\\Documents\\Ai-Ml\\Agentic Ai\\HireLoop\\HireLoop\\frontend\\src\\components\\ui\\tabs.jsx", "source_location": "L8", "weight": 1.0}, {"source": "c_users_tanis_onedrive_documents_ai_ml_agentic_ai_hireloop_hireloop_frontend_src_components_ui_tabs_jsx", "target": "ui_tabs_tabslist", "relation": "contains", "confidence": "EXTRACTED", "source_file": "C:\\Users\\tanis\\OneDrive\\Documents\\Ai-Ml\\Agentic Ai\\HireLoop\\HireLoop\\frontend\\src\\components\\ui\\tabs.jsx", "source_location": "L37", "weight": 1.0}, {"source": "c_users_tanis_onedrive_documents_ai_ml_agentic_ai_hireloop_hireloop_frontend_src_components_ui_tabs_jsx", "target": "ui_tabs_tabstrigger", "relation": "contains", "confidence": "EXTRACTED", "source_file": "C:\\Users\\tanis\\OneDrive\\Documents\\Ai-Ml\\Agentic Ai\\HireLoop\\HireLoop\\frontend\\src\\components\\ui\\tabs.jsx", "source_location": "L51", "weight": 1.0}, {"source": "c_users_tanis_onedrive_documents_ai_ml_agentic_ai_hireloop_hireloop_frontend_src_components_ui_tabs_jsx", "target": "ui_tabs_tabscontent", "relation": "contains", "confidence": "EXTRACTED", "source_file": "C:\\Users\\tanis\\OneDrive\\Documents\\Ai-Ml\\Agentic Ai\\HireLoop\\HireLoop\\frontend\\src\\components\\ui\\tabs.jsx", "source_location": "L69", "weight": 1.0}], "raw_calls": [{"caller_nid": "ui_tabs_tabs", "callee": "cn", "is_member_call": false, "source_file": "C:\\Users\\tanis\\OneDrive\\Documents\\Ai-Ml\\Agentic Ai\\HireLoop\\HireLoop\\frontend\\src\\components\\ui\\tabs.jsx", "source_location": "L17"}, {"caller_nid": "ui_tabs_tabslist", "callee": "cn", "is_member_call": false, "source_file": "C:\\Users\\tanis\\OneDrive\\Documents\\Ai-Ml\\Agentic Ai\\HireLoop\\HireLoop\\frontend\\src\\components\\ui\\tabs.jsx", "source_location": "L46"}, {"caller_nid": "ui_tabs_tabslist", "callee": "tabsListVariants", "is_member_call": false, "source_file": "C:\\Users\\tanis\\OneDrive\\Documents\\Ai-Ml\\Agentic Ai\\HireLoop\\HireLoop\\frontend\\src\\components\\ui\\tabs.jsx", "source_location": "L46"}, {"caller_nid": "ui_tabs_tabstrigger", "callee": "cn", "is_member_call": false, "source_file": "C:\\Users\\tanis\\OneDrive\\Documents\\Ai-Ml\\Agentic Ai\\HireLoop\\HireLoop\\frontend\\src\\components\\ui\\tabs.jsx", "source_location": "L58"}, {"caller_nid": "ui_tabs_tabscontent", "callee": "cn", "is_member_call": false, "source_file": "C:\\Users\\tanis\\OneDrive\\Documents\\Ai-Ml\\Agentic Ai\\HireLoop\\HireLoop\\frontend\\src\\components\\ui\\tabs.jsx", "source_location": "L76"}]}